LICENSE
MANIFEST.in
README
README.rst
setup.py
django_simple_select.egg-info/PKG-INFO
django_simple_select.egg-info/SOURCES.txt
django_simple_select.egg-info/dependency_links.txt
django_simple_select.egg-info/top_level.txt
simpleselect/__init__.py
simpleselect/fields.py
simpleselect/models.py
simpleselect/urls.py
simpleselect/views.py
simpleselect/widgets.py
simpleselect/static/simpleselect.js