Metadata-Version: 1.0
Name: django-simple-select
Version: 0.3
Summary: An autocompleting select widget for Django
Home-page: https://github.com/leo-the-manic/django-simple-select/
Author: leo-the-manic
Author-email: manicleo@gmail.com
License: UNKNOWN
Platform: UNKNOWN
